tkscenes/__init__.py
tkscenes/child.py
tkscenes/scene.py
tkscenes-0.1.2.dist-info/METADATA
tkscenes-0.1.2.dist-info/WHEEL
tkscenes-0.1.2.dist-info/top_level.txt
tkscenes-0.1.2.dist-info/RECORD
