Metadata-Version: 2.1
Name: tkscenes
Version: 0.1.2
Summary: A package for TKinter and CustomTKinter
Author-email: TonyLovesMusic <tony.tonylovescoding@example.com>
Project-URL: Homepage, https://github.com/TonyLovesCoding/tkscenes
Project-URL: Issues, https://github.com/TonyLovesCoding/tkscenes/issues
Classifier: Development Status :: 3 - Alpha
Classifier: Programming Language :: Python :: 3
Classifier: Operating System :: OS Independent
Requires-Python: >=3.12
